setup.py
daspos_umbrella.egg-info/PKG-INFO
daspos_umbrella.egg-info/SOURCES.txt
daspos_umbrella.egg-info/dependency_links.txt
daspos_umbrella.egg-info/top_level.txt
umbrella/__init__.py
umbrella/gui_umbrella_specification_validator.py
umbrella/misc.py
umbrella/tests.py
umbrella/umbrella_components.py
umbrella/umbrella_errors.py
umbrella/umbrella_file.py
umbrella/umbrella_specification.py
umbrella/unittests.py