Metadata-Version: 1.1
Name: daspos-umbrella
Version: 0.3.3
Summary: Core library for umbrella preservation software
Home-page: https://github.com/crcresearch/daspos-umbrella
Author: Center for Research Computing, University of Notre Dame
Author-email: CRCSupport@nd.edu
License: MIT License
Platform: UNKNOWN
Classifier: Development Status :: 3 - Alpha
Classifier: License :: OSI Approved :: MIT License
Classifier: Intended Audience :: Developers
Classifier: Operating System :: OS Independent
Classifier: Programming Language :: Python
Classifier: Programming Language :: Python :: 2
Classifier: Programming Language :: Python :: 2.7
Classifier: Topic :: Software Development :: Libraries :: Python Modules
